{
  "candidate_details": {
    "affidavit_id": "1775922757",
    "candidate_name": "P. Poomani",
    "candidate_name_json": "POOMANI. P.",
    "age": "28",
    "party": "Independent",
    "constituency": "57 Palacode Assembly Constituency",
    "pan": "GMDPP6512D",
    "phone": "9489169987",
    "email": "poomaniperumal156@gmail.com",
    "address": "123, Kondasamanahalli Village, Thandukaranahalli Post, Palacode Taluk - 636 808, Dharmapuri District",
    "combined_from": [
      "xls",
      "json"
    ],
    "education": "B.A (English) Krishna College, Krishnagiri 2018, D.Parl (Fifth Tamil Sangam 2025)",
    "profession": "Individual grocery shop"
  },
  "financial_summary": {
    "total_assets_xls": 6896000.0,
    "total_liabilities_xls": 4100000.0,
    "net_worth_xls": 2796000.0,
    "cash_xls": 20000.0
  },
  "asset_details": {
    "movable": {
      "Cash": {
        "self": "20,000 20 Thou+",
        "spouse": "20,000 20 Thou+",
        "huf": "Nil",
        "dependent1": "Nil",
        "dependent2": "Nil",
        "dependent3": "Nil"
      },
      "Deposits in Banks, Financial Institutions and Non-Banking Financial Companies": {
        "self": "DDDC Sugar Mill Palacode 1,000 1 Thou+",
        "spouse": "SBI, Palacode 5,000 5 Thou+",
        "huf": "Nil",
        "dependent1": "Nil",
        "dependent2": "Nil",
        "dependent3": "Nil"
      },
      "Bonds, Debentures and Shares in companies": {
        "self": "Nil",
        "spouse": "Nil",
        "huf": "Nil",
        "dependent1": "Nil",
        "dependent2": "Nil",
        "dependent3": "Nil"
      },
      "(a) NSS, Postal Savings etc": {
        "self": "Nil",
        "spouse": "Nil",
        "huf": "Nil",
        "dependent1": "Nil",
        "dependent2": "Nil",
        "dependent3": "Nil"
      },
      "(b) LIC or other insurance Policies": {
        "self": "Nil",
        "spouse": "Nil",
        "huf": "Nil",
        "dependent1": "Nil",
        "dependent2": "Nil",
        "dependent3": "Nil"
      },
      "Personal loans/advance given": {
        "self": "Nil",
        "spouse": "Nil",
        "huf": "Nil",
        "dependent1": "Nil",
        "dependent2": "Nil",
        "dependent3": "Nil"
      },
      "Motor Vehicles (details of make, etc.)": {
        "self": "Nil",
        "spouse": "TN-13-D-9048 Eco Sport Car 6,00,000 6 Lacs+",
        "huf": "Nil",
        "dependent1": "Nil",
        "dependent2": "Nil",
        "dependent3": "Nil"
      },
      "Jewellery (give details weight value)": {
        "self": "20 Gms 2,50,000 2 Lacs+",
        "spouse": "Nil",
        "huf": "Nil",
        "dependent1": "Nil",
        "dependent2": "Nil",
        "dependent3": "Nil"
      },
      "Other assets, such as values of claims / interests": {
        "self": "Nil",
        "spouse": "Nil",
        "huf": "Nil",
        "dependent1": "Nil",
        "dependent2": "Nil",
        "dependent3": "Nil"
      }
    },
    "immovable": {
      "Agricultural Land": {
        "self": "Nil",
        "spouse": "Thandukarana Alli, Survey No. 528/1A Total Area 0.40 Cents Built Up Area Whether Inherited Y Purchase Date 0000-00-00 Purchase Cost 0.00 Development Cost 0.00 10,00,000 10 Lacs+",
        "huf": "Nil",
        "dependent1": "Nil",
        "dependent2": "Nil",
        "dependent3": "Nil"
      },
      "Non Agricultural Land": {
        "self": "Nil",
        "spouse": "Thandukarana Alli, Survey No. 528/1C Total Area 0.05 Cents Built Up Area Whether Inherited Y Purchase Date 0000-00-00 Purchase Cost 0.00 Development Cost 0.00 5,00,000 5 Lacs+",
        "huf": "Nil",
        "dependent1": "Nil",
        "dependent2": "Nil",
        "dependent3": "Nil"
      },
      "Commercial Buildings": {
        "self": "Nil",
        "spouse": "Thandukarana Alli, Survey No. 544/3 Total Area 0.01 Cents Built Up Area Whether Inherited Y Purchase Date 0000-00-00 Purchase Cost 0.00 Development Cost 1000000.00 15,00,000 15 Lacs+",
        "huf": "Nil",
        "dependent1": "Nil",
        "dependent2": "Nil",
        "dependent3": "Nil"
      },
      "Residential Buildings": {
        "self": "Nil",
        "spouse": "Nil",
        "huf": "Nil",
        "dependent1": "Nil",
        "dependent2": "Nil",
        "dependent3": "Nil"
      },
      "Others": {
        "self": "Nil",
        "spouse": "Nil",
        "huf": "Nil",
        "dependent1": "Nil",
        "dependent2": "Nil",
        "dependent3": "Nil"
      }
    }
  },
  "liability_details": {
    "Loans from Banks / FIs": {
      "self": "Nil",
      "spouse": "HDB Finance 7,00,000 7 Lacs+ car Loan TVs Credit 3,50,000 3 Lacs+ Gold Loan 10,00,000 10 Lacs+",
      "huf": "Nil",
      "dependent1": "Nil",
      "dependent2": "Nil",
      "dependent3": "Nil"
    },
    "Loans due to Individual / Entity": {
      "self": "Nil",
      "spouse": "Nil",
      "huf": "Nil",
      "dependent1": "Nil",
      "dependent2": "Nil",
      "dependent3": "Nil"
    },
    "Any other Liability": {
      "self": "Nil",
      "spouse": "Nil",
      "huf": "Nil",
      "dependent1": "Nil",
      "dependent2": "Nil",
      "dependent3": "Nil"
    },
    "Dues to departments dealing with government accommodation": {
      "self": "Nil",
      "spouse": "Nil",
      "huf": "Nil",
      "dependent1": "Nil",
      "dependent2": "Nil",
      "dependent3": "Nil"
    },
    "Dues to departments dealing with supply of water": {
      "self": "Nil",
      "spouse": "Nil",
      "huf": "Nil",
      "dependent1": "Nil",
      "dependent2": "Nil",
      "dependent3": "Nil"
    },
    "Dues to departments dealing with supply of electricity": {
      "self": "Nil",
      "spouse": "Nil",
      "huf": "Nil",
      "dependent1": "Nil",
      "dependent2": "Nil",
      "dependent3": "Nil"
    },
    "Dues to departments dealing with telephones": {
      "self": "Nil",
      "spouse": "Nil",
      "huf": "Nil",
      "dependent1": "Nil",
      "dependent2": "Nil",
      "dependent3": "Nil"
    },
    "Dues to departments dealing with supply of transport": {
      "self": "Nil",
      "spouse": "Nil",
      "huf": "Nil",
      "dependent1": "Nil",
      "dependent2": "Nil",
      "dependent3": "Nil"
    },
    "Income Tax Dues": {
      "self": "Nil",
      "spouse": "Nil",
      "huf": "Nil",
      "dependent1": "Nil",
      "dependent2": "Nil",
      "dependent3": "Nil"
    },
    "Wealth Tax Dues": {
      "self": "Nil",
      "spouse": "Nil",
      "huf": "Nil",
      "dependent1": "Nil",
      "dependent2": "Nil",
      "dependent3": "Nil"
    },
    "Service Tax Dues": {
      "self": "Nil",
      "spouse": "Nil",
      "huf": "Nil",
      "dependent1": "Nil",
      "dependent2": "Nil",
      "dependent3": "Nil"
    },
    "Property Tax Dues": {
      "self": "Nil",
      "spouse": "Nil",
      "huf": "Nil",
      "dependent1": "Nil",
      "dependent2": "Nil",
      "dependent3": "Nil"
    },
    "Sales Tax Dues": {
      "self": "Nil",
      "spouse": "Nil",
      "huf": "Nil",
      "dependent1": "Nil",
      "dependent2": "Nil",
      "dependent3": "Nil"
    },
    "GST Dues": {
      "self": "Nil",
      "spouse": "Nil",
      "huf": "Nil",
      "dependent1": "Nil",
      "dependent2": "Nil",
      "dependent3": "Nil"
    },
    "Any Other Dues": {
      "self": "Nil",
      "spouse": "Nil",
      "huf": "Nil",
      "dependent1": "Nil",
      "dependent2": "Nil",
      "dependent3": "Nil"
    },
    "Whether any other liabilities are in dispute, if so, mention the amount involved and the authority before which it is pending": {
      "self": "Nil",
      "spouse": "Nil",
      "huf": "Nil",
      "dependent1": "Nil",
      "dependent2": "Nil",
      "dependent3": "Nil"
    }
  },
  "income_history": [
    {
      "relation": "self",
      "pan_given": "Y",
      "year": "None",
      "income": "Nil"
    },
    {
      "relation": "spouse",
      "pan_given": "Y",
      "year": "None",
      "income": "Nil"
    },
    {
      "relation": "huf",
      "pan_given": "Nil",
      "year": "Nil",
      "income": "Nil"
    },
    {
      "relation": "dependent1",
      "pan_given": "Nil",
      "year": "Nil",
      "income": "Nil"
    },
    {
      "relation": "dependent2",
      "pan_given": "Nil",
      "year": "Nil",
      "income": "Nil"
    },
    {
      "relation": "dependent3",
      "pan_given": "Nil",
      "year": "Nil",
      "income": "Nil"
    }
  ],
  "criminal_summary": {
    "criminal_status": "Clean",
    "case_numbers_xls": "NIL",
    "criminal_cases_json": {
      "count": "0",
      "summary": "No criminal cases",
      "ipc_charges": [],
      "pending_cases": [],
      "convicted_cases": []
    }
  },
  "asset_liability_summary": {
    "Assets:": "Rs 38,96,000 ~38 Lacs+",
    "Liabilities:": "Rs 20,50,000 ~20 Lacs+"
  },
  "discrepancies": [
    {
      "flag_id": "F6",
      "severity": "HIGH",
      "title": "Gold Loan Exceeds Expected LTV",
      "description": "Gold loans sum to ₹1,000,000 against declared gold value of ₹250,000 (exceeds 90% LTV)."
    },
    {
      "flag_id": "F6",
      "severity": "MEDIUM",
      "title": "Data Quality / Typo Anomaly",
      "description": "Found data quality issues: Invalid Date (0000-00-00)"
    }
  ]
}