{
  "candidate_details": {
    "affidavit_id": "1775915962",
    "candidate_name": "Sathishkumar S",
    "candidate_name_json": "C.SATHISHKUMAR",
    "age": "37",
    "party": "Independent",
    "constituency": "191 – Madurai North Assembly Constituency, Tamil Nadu",
    "pan": "GIXPS6971R",
    "phone": "9655505556",
    "email": "skrsry1989@gmail.com",
    "address": "Door No. 370, LIG Colony, Annanagar, Madurai- 625 020",
    "combined_from": [
      "xls",
      "json"
    ],
    "education": "10th standard, Private, 2012",
    "profession": "Salon shop owner"
  },
  "financial_summary": {
    "total_assets_xls": 6299550.0,
    "total_liabilities_xls": 33500000.0,
    "net_worth_xls": 27200450.0,
    "cash_xls": 1000.0
  },
  "asset_details": {
    "movable": {
      "Cash": {
        "self": "1,000 1 Thou+",
        "spouse": "2,000 2 Thou+",
        "huf": "Nil",
        "dependent1": "Nil",
        "dependent2": "Nil",
        "dependent3": "Nil"
      },
      "Deposits in Banks, Financial Institutions and Non-Banking Financial Companies": {
        "self": "Canara Bank,Thallakulam Branch,Madhurai ,SB 550 5 Hund+ Indian bank,Thallakulam Branch, Madhurai,SB, (Account for Election Purpose) 1,000 1 Thou+",
        "spouse": "Nil",
        "huf": "Nil",
        "dependent1": "Nil",
        "dependent2": "Nil",
        "dependent3": "Nil"
      },
      "Bonds, Debentures and Shares in companies": {
        "self": "Nil",
        "spouse": "Nil",
        "huf": "Nil",
        "dependent1": "Nil",
        "dependent2": "Nil",
        "dependent3": "Nil"
      },
      "(a) NSS, Postal Savings etc": {
        "self": "Nil",
        "spouse": "Nil",
        "huf": "Nil",
        "dependent1": "Nil",
        "dependent2": "Nil",
        "dependent3": "Nil"
      },
      "(b) LIC or other insurance Policies": {
        "self": "Nil",
        "spouse": "Nil",
        "huf": "Nil",
        "dependent1": "Nil",
        "dependent2": "Nil",
        "dependent3": "Nil"
      },
      "Personal loans/advance given": {
        "self": "Nil",
        "spouse": "Nil",
        "huf": "Nil",
        "dependent1": "Nil",
        "dependent2": "Nil",
        "dependent3": "Nil"
      },
      "Motor Vehicles (details of make, etc.)": {
        "self": "TVS Scooty Pep TN 64Z3324-Year :2023 50,000 50 Thou+",
        "spouse": "Nil",
        "huf": "Nil",
        "dependent1": "Nil",
        "dependent2": "Nil",
        "dependent3": "Nil"
      },
      "Jewellery (give details weight value)": {
        "self": "Nil",
        "spouse": "Gold Jewellery, 150 grams 12,45,000 12 Lacs+",
        "huf": "Nil",
        "dependent1": "Nil",
        "dependent2": "Nil",
        "dependent3": "Nil"
      },
      "Other assets, such as values of claims / interests": {
        "self": "Nil",
        "spouse": "Nil",
        "huf": "Nil",
        "dependent1": "Nil",
        "dependent2": "Nil",
        "dependent3": "Nil"
      }
    },
    "immovable": {
      "Agricultural Land": {
        "self": "Nil",
        "spouse": "Nil",
        "huf": "Nil",
        "dependent1": "Nil",
        "dependent2": "Nil",
        "dependent3": "Nil"
      },
      "Non Agricultural Land": {
        "self": "Nil",
        "spouse": "Nil",
        "huf": "Nil",
        "dependent1": "Nil",
        "dependent2": "Nil",
        "dependent3": "Nil"
      },
      "Commercial Buildings": {
        "self": "Nil",
        "spouse": "Nil",
        "huf": "Nil",
        "dependent1": "Nil",
        "dependent2": "Nil",
        "dependent3": "Nil"
      },
      "Residential Buildings": {
        "self": "Madurai Town,Madurai North Taluk,Satthamangalam Village ,S.No. 73/7G Total Area 525 Sqft Built Up Area Whether Inherited N Purchase Date 2023-08-28 Purchase Cost 2250000.00 Development Cost 100000.00 45,00,000 45 Lacs+",
        "spouse": "Nil",
        "huf": "Nil",
        "dependent1": "Nil",
        "dependent2": "Nil",
        "dependent3": "Nil"
      },
      "Others": {
        "self": "Nil",
        "spouse": "Nil",
        "huf": "Nil",
        "dependent1": "Nil",
        "dependent2": "Nil",
        "dependent3": "Nil"
      }
    }
  },
  "liability_details": {
    "Loans from Banks / FIs": {
      "self": "Canara Bank ,Thallakulam ,Jewel Loan 10,00,000 10 Lacs+ Canara Bank ,Thallakulam ,OD Loan 3,00,000 3 Lacs+ Canara Bank 50,000 50 Thou+ HDFC Housing Loan 20,00,000 20 Lacs+",
      "spouse": "Nil",
      "huf": "Nil",
      "dependent1": "Nil",
      "dependent2": "Nil",
      "dependent3": "Nil"
    },
    "Loans due to Individual / Entity": {
      "self": "Nil",
      "spouse": "Nil",
      "huf": "Nil",
      "dependent1": "Nil",
      "dependent2": "Nil",
      "dependent3": "Nil"
    },
    "Any other Liability": {
      "self": "Nil",
      "spouse": "Nil",
      "huf": "Nil",
      "dependent1": "Nil",
      "dependent2": "Nil",
      "dependent3": "Nil"
    },
    "Dues to departments dealing with government accommodation": {
      "self": "Nil",
      "spouse": "Nil",
      "huf": "Nil",
      "dependent1": "Nil",
      "dependent2": "Nil",
      "dependent3": "Nil"
    },
    "Dues to departments dealing with supply of water": {
      "self": "Nil",
      "spouse": "Nil",
      "huf": "Nil",
      "dependent1": "Nil",
      "dependent2": "Nil",
      "dependent3": "Nil"
    },
    "Dues to departments dealing with supply of electricity": {
      "self": "Nil",
      "spouse": "Nil",
      "huf": "Nil",
      "dependent1": "Nil",
      "dependent2": "Nil",
      "dependent3": "Nil"
    },
    "Dues to departments dealing with telephones": {
      "self": "Nil",
      "spouse": "Nil",
      "huf": "Nil",
      "dependent1": "Nil",
      "dependent2": "Nil",
      "dependent3": "Nil"
    },
    "Dues to departments dealing with supply of transport": {
      "self": "Nil",
      "spouse": "Nil",
      "huf": "Nil",
      "dependent1": "Nil",
      "dependent2": "Nil",
      "dependent3": "Nil"
    },
    "Income Tax Dues": {
      "self": "Nil",
      "spouse": "Nil",
      "huf": "Nil",
      "dependent1": "Nil",
      "dependent2": "Nil",
      "dependent3": "Nil"
    },
    "Wealth Tax Dues": {
      "self": "Nil",
      "spouse": "Nil",
      "huf": "Nil",
      "dependent1": "Nil",
      "dependent2": "Nil",
      "dependent3": "Nil"
    },
    "Service Tax Dues": {
      "self": "Nil",
      "spouse": "Nil",
      "huf": "Nil",
      "dependent1": "Nil",
      "dependent2": "Nil",
      "dependent3": "Nil"
    },
    "Property Tax Dues": {
      "self": "Nil",
      "spouse": "Nil",
      "huf": "Nil",
      "dependent1": "Nil",
      "dependent2": "Nil",
      "dependent3": "Nil"
    },
    "Sales Tax Dues": {
      "self": "Nil",
      "spouse": "Nil",
      "huf": "Nil",
      "dependent1": "Nil",
      "dependent2": "Nil",
      "dependent3": "Nil"
    },
    "GST Dues": {
      "self": "Nil",
      "spouse": "Nil",
      "huf": "Nil",
      "dependent1": "Nil",
      "dependent2": "Nil",
      "dependent3": "Nil"
    },
    "Any Other Dues": {
      "self": "Nil",
      "spouse": "Nil",
      "huf": "Nil",
      "dependent1": "Nil",
      "dependent2": "Nil",
      "dependent3": "Nil"
    },
    "Whether any other liabilities are in dispute, if so, mention the amount involved and the authority before which it is pending": {
      "self": "Nil",
      "spouse": "Nil",
      "huf": "Nil",
      "dependent1": "Nil",
      "dependent2": "Nil",
      "dependent3": "Nil"
    }
  },
  "income_history": [
    {
      "relation": "self",
      "pan_given": "Y",
      "year": "2024 - 2025",
      "income": "2024 - 2025: Rs 7,01,000 | 2023 - 2024: Rs 4,79,350 | 2022 - 2023: Rs 4,45,200 | 2021 - 2022: Rs 3,96,540"
    },
    {
      "relation": "spouse",
      "pan_given": "Y",
      "year": "None",
      "income": "Nil"
    },
    {
      "relation": "huf",
      "pan_given": "N",
      "year": "None",
      "income": "Nil"
    },
    {
      "relation": "dependent1",
      "pan_given": "N",
      "year": "None",
      "income": "Nil"
    },
    {
      "relation": "dependent2",
      "pan_given": "N",
      "year": "None",
      "income": "Nil"
    },
    {
      "relation": "dependent3",
      "pan_given": "N",
      "year": "None",
      "income": "Nil"
    }
  ],
  "criminal_summary": {
    "criminal_status": "Clean",
    "case_numbers_xls": "NIL",
    "criminal_cases_json": {
      "count": "0",
      "summary": "No criminal cases",
      "ipc_charges": [],
      "pending_cases": [],
      "convicted_cases": []
    }
  },
  "asset_liability_summary": {
    "Assets:": "Rs 57,99,550 ~57 Lacs+",
    "Liabilities:": "Rs 33,50,000 ~33 Lacs+"
  },
  "discrepancies": [
    {
      "flag_id": "F4",
      "severity": "CRITICAL",
      "title": "Gold Heavily Undervalued (Tax/Duty Evasion)",
      "description": "150.0g gold declared at ₹1,245,000 (Implied rate: ₹8,300/g vs April 2026 Market Rate of ~₹14,200/g)."
    }
  ]
}