{
  "candidate_details": {
    "affidavit_id": "1775925005",
    "candidate_name": "P. MILANY",
    "candidate_name_json": "P. MILANY",
    "age": "45",
    "party": "INDEPENDENT",
    "constituency": "200 BODINAYAKANUR ASSEMBLY CONSTITUENCY, TAMILNADU",
    "pan": "AOTPM5713K",
    "phone": "9500691041",
    "email": "milanyponnuram81@gmail.com",
    "address": "9, SANJAY GANDHI FIRST STREET, SELVARAJ ILLAM, PALANICHETTIPATTI, THENI DISTRICT, TAMILNADU-625531",
    "combined_from": [
      "xls",
      "json"
    ],
    "education": "Bachelor of Engineering (Mechanical) -- Coimbatore Institute of Technology, Bharathiar University -- 2002.",
    "profession": "agriculture"
  },
  "financial_summary": {
    "total_assets_xls": 2050313.78,
    "total_liabilities_xls": 11109722.0,
    "net_worth_xls": 9059408.22,
    "cash_xls": 130000.0
  },
  "asset_details": {
    "movable": {
      "Cash": {
        "self": "1,30,000 1 Lacs+",
        "spouse": "Nil",
        "huf": "Nil",
        "dependent1": "5,000 5 Thou+",
        "dependent2": "Nil",
        "dependent3": "Nil"
      },
      "Deposits in Banks, Financial Institutions and Non-Banking Financial Companies": {
        "self": "Federal Bank , Theni Br 2,286 2 Thou+ Bank of Maharastra , Theni Br ( election -13 -Kolathur) 4,999 4 Thou+ Post office Theni Br (Election Account, 19 Chepauk Thiruvallikeni ) 1,000 1 Thou+",
        "spouse": "Nil",
        "huf": "Nil",
        "dependent1": "Nil",
        "dependent2": "Nil",
        "dependent3": "Nil"
      },
      "Bonds, Debentures and Shares in companies": {
        "self": "Nil",
        "spouse": "Nil",
        "huf": "Nil",
        "dependent1": "Nil",
        "dependent2": "Nil",
        "dependent3": "Nil"
      },
      "(a) NSS, Postal Savings etc": {
        "self": "Nil",
        "spouse": "Nil",
        "huf": "Nil",
        "dependent1": "Nil",
        "dependent2": "Nil",
        "dependent3": "Nil"
      },
      "(b) LIC or other insurance Policies": {
        "self": "Nil",
        "spouse": "Nil",
        "huf": "Nil",
        "dependent1": "Nil",
        "dependent2": "Nil",
        "dependent3": "Nil"
      },
      "Personal loans/advance given": {
        "self": "Nil",
        "spouse": "Nil",
        "huf": "Nil",
        "dependent1": "Nil",
        "dependent2": "Nil",
        "dependent3": "Nil"
      },
      "Motor Vehicles (details of make, etc.)": {
        "self": "Mahindra Bolero TN 60 AD 68888 2018 8,41,428 8 Lacs+",
        "spouse": "Nil",
        "huf": "Nil",
        "dependent1": "Nil",
        "dependent2": "Nil",
        "dependent3": "Nil"
      },
      "Jewellery (give details weight value)": {
        "self": "Nil",
        "spouse": "Nil",
        "huf": "Nil",
        "dependent1": "Nil",
        "dependent2": "Nil",
        "dependent3": "Nil"
      },
      "Other assets, such as values of claims / interests": {
        "self": "Nil",
        "spouse": "Nil",
        "huf": "Nil",
        "dependent1": "Nil",
        "dependent2": "Nil",
        "dependent3": "Nil"
      }
    },
    "immovable": {
      "Agricultural Land": {
        "self": "1. Poomalaigunda Revenue Village Tauk, Theni Taluk, Theni Sub Registrar Office SY No.437/2B, 437/7, 438/1A 2. Poomalaigunda Revenue Village Tauk, Theni Taluk, Theni Sub Registrar Office SY No.438/1C Areas : 5.03, 0.06 (2/3Share of joint patta) Total Area Built Up Area Whether Inherited N Purchase Date 2019-01-29 Purchase Cost 0.00 Development Cost 0.00 10,70,600 10 Lacs+",
        "spouse": "Nil",
        "huf": "Nil",
        "dependent1": "Nil",
        "dependent2": "Nil",
        "dependent3": "Nil"
      },
      "Non Agricultural Land": {
        "self": "Nil",
        "spouse": "Nil",
        "huf": "Nil",
        "dependent1": "Nil",
        "dependent2": "Nil",
        "dependent3": "Nil"
      },
      "Commercial Buildings": {
        "self": "Nil",
        "spouse": "Nil",
        "huf": "Nil",
        "dependent1": "Nil",
        "dependent2": "Nil",
        "dependent3": "Nil"
      },
      "Residential Buildings": {
        "self": "Nil",
        "spouse": "Nil",
        "huf": "Nil",
        "dependent1": "Nil",
        "dependent2": "Nil",
        "dependent3": "Nil"
      },
      "Others": {
        "self": "Nil",
        "spouse": "Nil",
        "huf": "Nil",
        "dependent1": "Nil",
        "dependent2": "Nil",
        "dependent3": "Nil"
      }
    }
  },
  "liability_details": {
    "Loans from Banks / FIs": {
      "self": "Axis Bank KCC Loan 4,24,534 4 Lacs+ Axis Bank KCC Loan 1,22,398 1 Lacs+ Balaji Finance Personal loan 2,84,995 2 Lacs+ Balaji Finance Personal loan 27,795 27 Thou+",
      "spouse": "Nil",
      "huf": "Nil",
      "dependent1": "Nil",
      "dependent2": "Nil",
      "dependent3": "Nil"
    },
    "Loans due to Individual / Entity": {
      "self": "Nil",
      "spouse": "Nil",
      "huf": "Nil",
      "dependent1": "Nil",
      "dependent2": "Nil",
      "dependent3": "Nil"
    },
    "Any other Liability": {
      "self": "Gurantee given to Shriram Finance Commercial Vehicle Loan 17,50,000 17 Lacs+ Gurantee given to Shriram Finance Commercial Vehicle Loan 26,50,000 26 Lacs+ Gurantee given to Shriram Finance Commercial Vehicle Loan 16,50,000 16 Lacs+ Gurantee given to Shriram Finance Commercial Vehicle Loan 21,00,000 21 Lacs+ Gurantee given to Shriram Finance Commercial Vehicle Loan 21,00,000 21 Lacs+",
      "spouse": "Nil",
      "huf": "Nil",
      "dependent1": "Nil",
      "dependent2": "Nil",
      "dependent3": "Nil"
    },
    "Dues to departments dealing with government accommodation": {
      "self": "Nil",
      "spouse": "Nil",
      "huf": "Nil",
      "dependent1": "Nil",
      "dependent2": "Nil",
      "dependent3": "Nil"
    },
    "Dues to departments dealing with supply of water": {
      "self": "Nil",
      "spouse": "Nil",
      "huf": "Nil",
      "dependent1": "Nil",
      "dependent2": "Nil",
      "dependent3": "Nil"
    },
    "Dues to departments dealing with supply of electricity": {
      "self": "Nil",
      "spouse": "Nil",
      "huf": "Nil",
      "dependent1": "Nil",
      "dependent2": "Nil",
      "dependent3": "Nil"
    },
    "Dues to departments dealing with telephones": {
      "self": "Nil",
      "spouse": "Nil",
      "huf": "Nil",
      "dependent1": "Nil",
      "dependent2": "Nil",
      "dependent3": "Nil"
    },
    "Dues to departments dealing with supply of transport": {
      "self": "Nil",
      "spouse": "Nil",
      "huf": "Nil",
      "dependent1": "Nil",
      "dependent2": "Nil",
      "dependent3": "Nil"
    },
    "Income Tax Dues": {
      "self": "Nil",
      "spouse": "Nil",
      "huf": "Nil",
      "dependent1": "Nil",
      "dependent2": "Nil",
      "dependent3": "Nil"
    },
    "Wealth Tax Dues": {
      "self": "Nil",
      "spouse": "Nil",
      "huf": "Nil",
      "dependent1": "Nil",
      "dependent2": "Nil",
      "dependent3": "Nil"
    },
    "Service Tax Dues": {
      "self": "Nil",
      "spouse": "Nil",
      "huf": "Nil",
      "dependent1": "Nil",
      "dependent2": "Nil",
      "dependent3": "Nil"
    },
    "Property Tax Dues": {
      "self": "Nil",
      "spouse": "Nil",
      "huf": "Nil",
      "dependent1": "Nil",
      "dependent2": "Nil",
      "dependent3": "Nil"
    },
    "Sales Tax Dues": {
      "self": "Nil",
      "spouse": "Nil",
      "huf": "Nil",
      "dependent1": "Nil",
      "dependent2": "Nil",
      "dependent3": "Nil"
    },
    "GST Dues": {
      "self": "Nil",
      "spouse": "Nil",
      "huf": "Nil",
      "dependent1": "Nil",
      "dependent2": "Nil",
      "dependent3": "Nil"
    },
    "Any Other Dues": {
      "self": "Nil",
      "spouse": "Nil",
      "huf": "Nil",
      "dependent1": "Nil",
      "dependent2": "Nil",
      "dependent3": "Nil"
    },
    "Whether any other liabilities are in dispute, if so, mention the amount involved and the authority before which it is pending": {
      "self": "Nil",
      "spouse": "Nil",
      "huf": "Nil",
      "dependent1": "Nil",
      "dependent2": "Nil",
      "dependent3": "Nil"
    }
  },
  "income_history": [
    {
      "relation": "self",
      "pan_given": "Y",
      "year": "None",
      "income": "Nil"
    },
    {
      "relation": "spouse",
      "pan_given": "Nil",
      "year": "Nil",
      "income": "Nil"
    },
    {
      "relation": "huf",
      "pan_given": "Nil",
      "year": "Nil",
      "income": "Nil"
    },
    {
      "relation": "dependent1",
      "pan_given": "Y",
      "year": "None",
      "income": "Nil"
    },
    {
      "relation": "dependent2",
      "pan_given": "Nil",
      "year": "Nil",
      "income": "Nil"
    },
    {
      "relation": "dependent3",
      "pan_given": "Nil",
      "year": "Nil",
      "income": "Nil"
    }
  ],
  "criminal_summary": {
    "criminal_status": "Pending (6 case(s))",
    "case_numbers_xls": "277/2018 - CUMBUM SOUTH PS; 53/2018 - VEERAPANDI PS; 28/2016 - VEERAPANDI PS; 18/2016 - VEERAPANDI PS; 69/2015 - VEERAPANDI PS; 47/2015 - VEERAPANDI PS",
    "criminal_cases_json": {
      "count": "6",
      "summary": "Number of Criminal Cases:6",
      "ipc_charges": [
        "1 charges related to Voluntarily causing hurt by dangerous weapons or means (IPC Section-324)",
        "2 charges related to Punishment for Rioting (IPC Section-147)",
        "1 charges related to Punishment of abetment if the act abetted is committed in consequence, and where no express provision is made for its punishment (IPC Section-109)",
        "1 charges related to Rioting, armed with deadly weapon (IPC Section-148)",
        "1 charges related to Punishment for voluntarily causing hurt (IPC Section-323)",
        "1 charges related to Punishment for wrongful restraint (IPC Section-341)"
      ],
      "pending_cases": [
        {
          "serial_no": "1",
          "fir_no": "277/2018 Cumbum South Police Station",
          "case_no": "Nil",
          "court": "Nil",
          "law_type": "IPC",
          "ipc_sections": "Nil",
          "other_details": "Section-151 CRPC",
          "charges_framed": "No",
          "charges_date": "Nil",
          "appeal_filed": "No",
          "appeal_status": "Nil"
        },
        {
          "serial_no": "2",
          "fir_no": "53/2018 Veeranpadi Police station",
          "case_no": "Nil",
          "court": "Nil",
          "law_type": "IPC",
          "ipc_sections": "Nil",
          "other_details": "Section-151 CRPC",
          "charges_framed": "No",
          "charges_date": "Nil",
          "appeal_filed": "No",
          "appeal_status": "Nil"
        },
        {
          "serial_no": "3",
          "fir_no": "28/2016 Veeranpadi Police station",
          "case_no": "Nil",
          "court": "Nil",
          "law_type": "IPC",
          "ipc_sections": "Nil",
          "other_details": "Section-107 CRPC",
          "charges_framed": "No",
          "charges_date": "Nil",
          "appeal_filed": "No",
          "appeal_status": "Nil"
        },
        {
          "serial_no": "4",
          "fir_no": "18/2016 Veeranpadi Police station",
          "case_no": "Nil",
          "court": "Nil",
          "law_type": "IPC",
          "ipc_sections": "109, 147, 148, 294(b), 323, 324, 341, 506(2)",
          "other_details": "Nil",
          "charges_framed": "No",
          "charges_date": "Nil",
          "appeal_filed": "No",
          "appeal_status": "Nil"
        },
        {
          "serial_no": "5",
          "fir_no": "69/2015 Veeranpadi Police station",
          "case_no": "Nil",
          "court": "Nil",
          "law_type": "IPC",
          "ipc_sections": "147, 294(b), 506(1)",
          "other_details": "Sec. 3(1)(i), 3(2)(v) of The Scheduled cast and the scheduled Tribes (Prevention of Atrocities)Amendment Ordinance 2014",
          "charges_framed": "No",
          "charges_date": "Nil",
          "appeal_filed": "No",
          "appeal_status": "Nil"
        },
        {
          "serial_no": "6",
          "fir_no": "47/2015 Veeranpadi Police station",
          "case_no": "Nil",
          "court": "Nil",
          "law_type": "IPC",
          "ipc_sections": "Nil",
          "other_details": "Section-107 CRPC",
          "charges_framed": "No",
          "charges_date": "Nil",
          "appeal_filed": "No",
          "appeal_status": "Nil"
        }
      ],
      "convicted_cases": []
    }
  },
  "asset_liability_summary": {
    "Assets:": "Rs 20,55,313 ~20 Lacs+",
    "Liabilities:": "Rs 1,11,09,722 ~1 Crore+"
  },
  "discrepancies": []
}